LICENSE
README.md
pyproject.toml
requirements.txt
rfproximity/__init__.py
rfproximity/version.py
rfproximity.egg-info/PKG-INFO
rfproximity.egg-info/SOURCES.txt
rfproximity.egg-info/dependency_links.txt
rfproximity.egg-info/requires.txt
rfproximity.egg-info/top_level.txt
rfproximity/similarityexplainer/__init__.py
rfproximity/similarityexplainer/similarityexplainer.py
rfproximity/treeimputer/__init__.py
rfproximity/treeimputer/imputerutils.py
rfproximity/treeimputer/treeimputer.py
rfproximity/treeimputer/treeimputermissingtarget.py
rfproximity/treeimputer/treeimputertest.py
rfproximity/treeproximity/__init__.py
rfproximity/treeproximity/treeproximity.py
test/test_imputerutils.py
test/test_similarityexplainer.py
test/test_treeimputer.py
test/test_treeimputermissingtarget.py
test/test_treeimputertest.py
test/test_treeproximity.py