Metadata-Version: 2.2
Name: rfproximity
Version: 0.0.2a1
Summary: RFProximity
Author-email: Dhruv Desai <dhruv.d25@gmail.com>
Classifier: Programming Language :: Python :: 3
Classifier: License :: OSI Approved :: Apache Software License
Classifier: Operating System :: OS Independent
Requires-Python: >=3.7
License-File: LICENSE
Requires-Dist: pandas>=0.24.2
Requires-Dist: category_encoders>=2.6.2
Requires-Dist: numpy>=0.24.2
Requires-Dist: scikit-learn>=0.21.2
